datadigitizer/__init__.py
datadigitizer/gui.py
datadigitizer/icon.png
datadigitizer/icon.py
datadigitizer/settings.py
datadigitizer/tests.py
datadigitizer/version.py
datadigitizer-1.3.0.dist-info/LICENSE
datadigitizer-1.3.0.dist-info/METADATA
datadigitizer-1.3.0.dist-info/WHEEL
datadigitizer-1.3.0.dist-info/entry_points.txt
datadigitizer-1.3.0.dist-info/top_level.txt
datadigitizer-1.3.0.dist-info/RECORD
