Metadata-Version: 2.1
Name: datadigitizer
Version: 1.3.0
Summary: datadigitizer: Data digitizer.
Author-email: Milan Skocic <milan.skocic@icloud.com>
License: MIT
Project-URL: Documentation, https://milanskocic.github.io/pydatadigitizer/index.html
Project-URL: Source, https://github.com/MilanSkocic/pydatadigitizer
Classifier: Development Status :: 5 - Production/Stable
Classifier: Intended Audience :: Science/Research
Classifier: Topic :: Scientific/Engineering
Classifier: License :: OSI Approved :: MIT License
Requires-Python: >=3.9
License-File: LICENSE
Requires-Dist: numpy>=1.22
Requires-Dist: matplotlib>=3.4.0
Requires-Dist: Pillow>=9.0.0
